besser/__init__.py
besser/bot/__init__.py
besser/bot/core/__init__.py
besser/bot/core/bot.py
besser/bot/core/file.py
besser/bot/core/message.py
besser/bot/core/property.py
besser/bot/core/session.py
besser/bot/core/state.py
besser/bot/core/transition.py
besser/bot/core/entity/__init__.py
besser/bot/core/entity/entity.py
besser/bot/core/entity/entity_entry.py
besser/bot/core/intent/__init__.py
besser/bot/core/intent/intent.py
besser/bot/core/intent/intent_parameter.py
besser/bot/core/processors/__init__.py
besser/bot/core/processors/language_detection_processor.py
besser/bot/core/processors/processor.py
besser/bot/core/processors/user_adaptation_processor.py
besser/bot/db/__init__.py
besser/bot/db/monitoring_db.py
besser/bot/db/monitoring_ui/__init__.py
besser/bot/db/monitoring_ui/db_connection.py
besser/bot/db/monitoring_ui/flow_graph.py
besser/bot/db/monitoring_ui/home.py
besser/bot/db/monitoring_ui/intent_details.py
besser/bot/db/monitoring_ui/monitoring_ui.py
besser/bot/db/monitoring_ui/sidebar.py
besser/bot/db/monitoring_ui/table_overview.py
besser/bot/db/monitoring_ui/utils.py
besser/bot/exceptions/__init__.py
besser/bot/exceptions/exceptions.py
besser/bot/library/__init__.py
besser/bot/library/entity/__init__.py
besser/bot/library/entity/base_entities.py
besser/bot/library/event/__init__.py
besser/bot/library/event/event_library.py
besser/bot/library/event/event_template.py
besser/bot/library/intent/__init__.py
besser/bot/library/intent/intent_library.py
besser/bot/library/state/__init__.py
besser/bot/library/state/state_library.py
besser/bot/nlp/__init__.py
besser/bot/nlp/nlp_engine.py
besser/bot/nlp/utils.py
besser/bot/nlp/intent_classifier/__init__.py
besser/bot/nlp/intent_classifier/intent_classifier.py
besser/bot/nlp/intent_classifier/intent_classifier_configuration.py
besser/bot/nlp/intent_classifier/intent_classifier_prediction.py
besser/bot/nlp/intent_classifier/llm_intent_classifier.py
besser/bot/nlp/intent_classifier/simple_intent_classifier.py
besser_bot_framework-1.5.0.dist-info/LICENSE
besser_bot_framework-1.5.0.dist-info/METADATA
besser_bot_framework-1.5.0.dist-info/WHEEL
besser_bot_framework-1.5.0.dist-info/top_level.txt
besser_bot_framework-1.5.0.dist-info/RECORD
