Metadata-Version: 2.1
Name: besser-bot-framework
Version: 1.5.0
Summary: BESSER Bot Framework (BBF)
Author: Luxembourg Institute of Science and Technology
License: MIT
Project-URL: Documentation, https://besser-bot-framework.readthedocs.io/
Project-URL: Source Code, https://github.com/BESSER-PEARL/BESSER-Bot-Framework
Project-URL: Bug Tracker, https://github.com/BESSER-PEARL/BESSER-Bot-Framework/issues
Keywords: bot,framework,chatbot,state-machine,nlp
Requires-Python: >=3.10
License-File: LICENSE
Requires-Dist: chromadb==0.5.4
Requires-Dist: dateparser==1.1.8
Requires-Dist: keras==2.14.0
Requires-Dist: langchain==0.2.9
Requires-Dist: langchain-community==0.2.7
Requires-Dist: langdetect==1.0.9
Requires-Dist: librosa==0.10.1
Requires-Dist: nltk==3.8.1
Requires-Dist: numpy==1.26.1
Requires-Dist: openai==1.24.0
Requires-Dist: pandas==2.1.1
Requires-Dist: plotly==5.18.0
Requires-Dist: psycopg2-binary==2.9.9
Requires-Dist: pypdf==4.3.1
Requires-Dist: python-telegram-bot==21.0
Requires-Dist: pyvis==0.3.2
Requires-Dist: replicate==0.23.1
Requires-Dist: requests==2.31.0
Requires-Dist: snowballstemmer==2.2.0
Requires-Dist: spacy==3.7.2
Requires-Dist: SpeechRecognition==3.10.0
Requires-Dist: sqlalchemy==2.0.29
Requires-Dist: streamlit==1.40.0
Requires-Dist: streamlit-antd-components==0.3.2
Requires-Dist: tensorflow==2.14.0
Requires-Dist: text2num==2.5.0
Requires-Dist: tiktoken==0.7.0
Requires-Dist: transformers==4.41.1
Requires-Dist: websocket-client==1.6.4
Requires-Dist: websockets==11.0.3
